{
  "source": {
    "source_id": "SRC-HNN-501F276BD93A900A",
    "url_id": "URL-501F276BD93A900A",
    "url": "https://hologramnews.com/star-atlas-dao-passes-first-two-governance-proposals",
    "title": "Star Atlas DAO passes first two governance proposals",
    "author": "Krigs",
    "publisher": "Hologram News Network (HNN)",
    "publication_identity": "HNN website (hologramnews.com)",
    "published_at": "2024-07-23T23:37:43+00:00",
    "updated_at": "2024-07-23T23:37:43+00:00",
    "retrieved_at": "2026-07-13T00:07:36.896213Z",
    "document_type": "ORIGINAL_REPORTING",
    "source_role": "ORIGINAL_REPORTING",
    "publication_role": "ORIGINAL_REPORTING",
    "classification_rationale": "Publication reports a development without explicit interview, editorial, investigative, event, or reference framing."
  },
  "source_lineage": {
    "publication": "HNN website (hologramnews.com)",
    "publication_role": "ORIGINAL_REPORTING",
    "relationship": "REPORTS_ON",
    "primary_sources": [
      {
        "publication": "PIP-1: The Framework for the Star Atlas DAO",
        "author": "UNKNOWN",
        "url": "https://govern.staratlas.com/proposals/bc8475e4-0525-4fba-b4f8-b848ccde7a9d",
        "organization": "UNKNOWN",
        "evidence": "Directly linked and named in the publication."
      },
      {
        "publication": "PIP-2: The Star Atlas Foundation passed by a slightly narrower margin",
        "author": "UNKNOWN",
        "url": "https://govern.staratlas.com/proposals/1e2d7066-ec44-46e0-945f-b2e56b1e61b0",
        "organization": "UNKNOWN",
        "evidence": "Directly linked and named in the publication."
      },
      {
        "publication": "The Council on Foreign Relations",
        "author": "UNKNOWN",
        "url": "https://www.cfr.org/in-brief/how-does-us-voter-turnout-compare-rest-worlds",
        "organization": "UNKNOWN",
        "evidence": "Directly linked and named in the publication."
      }
    ],
    "original_creators": [
      "Krigs"
    ],
    "attribution_chain": [
      {
        "from": "PIP-1: The Framework for the Star Atlas DAO",
        "to": "HNN website (hologramnews.com)",
        "relationship": "REPORTS_ON",
        "url": "https://govern.staratlas.com/proposals/bc8475e4-0525-4fba-b4f8-b848ccde7a9d"
      },
      {
        "from": "PIP-2: The Star Atlas Foundation passed by a slightly narrower margin",
        "to": "HNN website (hologramnews.com)",
        "relationship": "REPORTS_ON",
        "url": "https://govern.staratlas.com/proposals/1e2d7066-ec44-46e0-945f-b2e56b1e61b0"
      },
      {
        "from": "The Council on Foreign Relations",
        "to": "HNN website (hologramnews.com)",
        "relationship": "REPORTS_ON",
        "url": "https://www.cfr.org/in-brief/how-does-us-voter-turnout-compare-rest-worlds"
      }
    ],
    "lineage_confidence": "HIGH"
  },
  "summary": {
    "archival_abstract": "This original reporting published by Hologram News Network (HNN) on 2024-07-23 documents “Star Atlas DAO passes first two governance proposals.” Its surviving text addresses governance, economy, game development, community, lore, technology. The record is preserved as contemporary evidence of how HNN presented the subject at publication time; factual and forward-looking claims remain attributed to the publication and require reconciliation with primary or later sources.",
    "historical_value": "Preserves the HNN publication as contemporary community journalism and evidence of the network's editorial record.",
    "current_validity_warning": "Claims reflect the publication date and may have been superseded, corrected, or disproven."
  },
  "article_text": "Star Atlas DAO passes first two governance proposals\nBy KrigsPublished On: 24 July 2024Tags: dao, Polis, Star Atlas Politics\nIn a historic day for Star Atlas governance, the citizens of Galia voted to pass the first two proposals for the Star Atlas DAO. Over the last two weeks, voters took to the figurative ballot box to cast their votes.\nBoth measures passed by a large margin of votes. PIP-1: The Framework for the Star Atlas DAO, passed in a landslide with 118 million Polis voting power in support. 51 million Polis voting power voted against the measure with the main argument being that the proposals lacked the specificity required to administer proper governance. Additionally, citizens were concerned that the proposals gave too much power to the Foundation, and that voter’s rights were not adequately represented.\nAt one point mid-way through voting, the were more votes against the the proposals than for it. However, a late surge in votes pushed the proposals definitively past the 50% majority threshold required for passage.\nPIP-2: The Star Atlas Foundation passed by a slightly narrower margin with 100 million Polis voting power in support against 69 million against. PIP-2 outlines the scope, roles, and responsibilities of the Star Atlas Foundation, a legal entity that represents the DAO in legal matters within the physical realm.\nVoter turnout for both proposals was 894 and 852 respectively. Its important to note that citizens can hold Polis across multiple votes and that a single individual can account for multiple votes. Given the nature of the blockchain, voter fraud concerns are near zero, but it does raise valid discussion on various ways to measure voter participation.\nA comparative average of multiple DAOs across blockchain communities find that 20% participation is the mean average for DAOs. This is slightly lower than traditional electoral systems where the average voter turnout is approximately 35% for non-primary elections and generally above 60% for general elections.\nThe Council on Foreign Relations, a peer-reviewed academic journal, measures voter turnout and generally ascribes good voter participation rates in the 70th percent ranges.\nVoters now head back to voting box to vote on PIP-3 and PIP-4. PIP-3 established the Star Atlas Council, an elected body of Star Atlas citizens who assist the DAO in the law making process. PIP-4 establishes the Star Atlas Ecosystem fund, a budgetary line of allocation of the DAO treasury to fund community driven Star Atlas projects that intend on expanding the ecosystem.\nAbout the Author: Krigs\nAn ardent supporter of emerging technologies, Krigs has been covering blockchain games for over two years and believes passionately in their power to revolutionize our collective gaming experience.\nStar Atlas Discount\nSave 10% on Star Atlas with the Starpath Referral Program\nrelated\nStar Atlas Throwdown: Score VS Sage (Part 1)\nStar Atlas Begins Staff Reductions\nnews via inbox\nGet news from the Hologram first",
  "content_hash": "7f854da20f69cf4290679b8b216689fbd358748e818536ef310a71c6e70e2fe4",
  "major_topics": [
    "governance",
    "economy",
    "game development",
    "community",
    "lore",
    "technology"
  ],
  "entities": [
    "ATLAS",
    "Krigs",
    "POLIS",
    "SAGE",
    "SCORE",
    "Star Atlas",
    "StarPath"
  ],
  "events": [],
  "claims": [
    {
      "claim_id": "CLM-501F276BD93A900A-01",
      "text": "Star Atlas DAO passes first two governance proposals By KrigsPublished On: 24 July 2024Tags: dao, Polis, Star Atlas Politics In a historic day for Star Atlas governance, the citizens of Galia voted to pass the first two proposals for the Star Atlas DAO.",
      "claim_type": "RETROSPECTIVE_CLAIM",
      "speaker": "UNKNOWN",
      "reported_by": "Hologram News Network (HNN)",
      "source_id": "SRC-HNN-501F276BD93A900A",
      "confidence": "LOW",
      "requires_follow_up": true
    },
    {
      "claim_id": "CLM-501F276BD93A900A-02",
      "text": "51 million Polis voting power voted against the measure with the main argument being that the proposals lacked the specificity required to administer proper governance.",
      "claim_type": "RETROSPECTIVE_CLAIM",
      "speaker": "UNKNOWN",
      "reported_by": "Hologram News Network (HNN)",
      "source_id": "SRC-HNN-501F276BD93A900A",
      "confidence": "LOW",
      "requires_follow_up": true
    }
  ],
  "quotes": [],
  "relationships": [],
  "products": [
    "SAGE",
    "SCORE",
    "Star Atlas",
    "POLIS",
    "ATLAS",
    "StarPath"
  ],
  "governance_items": [
    "Star Atlas governance / DAO"
  ],
  "lore_items": [
    "ONI"
  ],
  "actors": [
    "Krigs"
  ],
  "guilds": [],
  "external_sources": [
    {
      "url": "https://hologramnews.com/star-atlas-dao-passes-first-two-governance-proposals/",
      "anchor_text": ""
    },
    {
      "url": "https://hologramnews.com/author/krigs/",
      "anchor_text": "Krigs"
    },
    {
      "url": "https://hologramnews.com/tag/dao/",
      "anchor_text": "dao"
    },
    {
      "url": "https://hologramnews.com/tag/polis6/",
      "anchor_text": "Polis"
    },
    {
      "url": "https://hologramnews.com/tag/politics/",
      "anchor_text": "Star Atlas Politics"
    },
    {
      "url": "https://hologramnews.com/star-atlas-news/",
      "anchor_text": "Star Atlas"
    },
    {
      "url": "https://hologramnews.com/star-atlas-dao-proposals-spark-intense-debate-on-governance/",
      "anchor_text": "first two proposals for the Star Atlas DAO."
    },
    {
      "url": "https://govern.staratlas.com/proposals/bc8475e4-0525-4fba-b4f8-b848ccde7a9d",
      "anchor_text": "PIP-1: The Framework for the Star Atlas DAO"
    },
    {
      "url": "https://govern.staratlas.com/proposals/1e2d7066-ec44-46e0-945f-b2e56b1e61b0",
      "anchor_text": "PIP-2: The Star Atlas Foundation passed by a slightly narrower margin"
    },
    {
      "url": "https://www.cfr.org/in-brief/how-does-us-voter-turnout-compare-rest-worlds",
      "anchor_text": "The Council on Foreign Relations"
    },
    {
      "url": "https://hologramnews.com/starpath-save-10-on-star-atlas/",
      "anchor_text": ""
    },
    {
      "url": "https://hologramnews.com/star-atlas-throwdown-score-vs-sage-part-1/",
      "anchor_text": ""
    },
    {
      "url": "https://hologramnews.com/star-atlas-begins-staff-reductions/",
      "anchor_text": ""
    }
  ],
  "open_questions": [
    "Which reported claims can be corroborated by primary or later sources?"
  ],
  "temporal_status": "HISTORICAL_SNAPSHOT",
  "current_validity": "REQUIRES_RECONCILIATION",
  "quality": {
    "extraction_confidence": "HIGH",
    "date_confidence": "HIGH",
    "author_confidence": "HIGH",
    "completeness": "COMPLETE",
    "manual_review_reasons": []
  },
  "retrieval": {
    "requested_url": "https://web.archive.org/web/20241210115142id_/https://hologramnews.com/star-atlas-dao-passes-first-two-governance-proposals/",
    "final_url": "https://web.archive.org/web/20241210115142id_/https://hologramnews.com/star-atlas-dao-passes-first-two-governance-proposals/",
    "http_status": 200,
    "content_type": "text/html; charset=UTF-8",
    "response_size": 195780,
    "elapsed_ms": 4965,
    "retrieval_mode": "INTERNET_ARCHIVE",
    "archive_capture": {
      "timestamp": "20241210115142",
      "original": "https://hologramnews.com/star-atlas-dao-passes-first-two-governance-proposals/",
      "digest": "GJRPYCUH56RNNEZ5TSRQTM6HZJNZGLCR"
    }
  }
}
