{
  "source": {
    "source_id": "SRC-AEPHIA-F99489EFB21C0054",
    "url_id": "URL-F99489EFB21C0054",
    "url": "https://aephia.com/star-atlas/town-hall-report-june-4-2025/",
    "inventory_url": "https://aephia.com/star-atlas/town-hall-report-june-4-2025",
    "title": "Town Hall Report – June 4, 2025",
    "author": "Aephia",
    "publisher": "Aephia",
    "published_at": "2025-06-04T21:22:31",
    "updated_at": "2025-06-12T12:34:28",
    "retrieved_at": "2026-07-12T21:41:04.062090Z",
    "document_type": "TOWN_HALL_REPORT",
    "source_role": "COMMUNITY_INSTITUTION"
  },
  "summary": {
    "neutral_abstract": "Michael (CEO) and Santi (VP of Community & Ecosystem) joined the stage to host the first Town Hall of the year, almost 6 months after the last one! While on stage, they were joined by various other team members to go over most of the alpha related to the topic at hand: If you missed the Town Hall and want to watch the full event, then be sure to check out the recording! In addition to the lengthy report below, the team has also composed a shorter summary of the event, which can be found on their Medium account. Note that our report also takes into account some clarifications and extensions provided on Discord and the Economic Forum that took place the following",
    "historical_value": "Contemporary Aephia coverage preserved as a community-institution source.",
    "current_validity_warning": "Operational, economic, governance, and roadmap statements may be historical and require reconciliation with later primary sources."
  },
  "article_text": "Michael (CEO) and Santi (VP of Community & Ecosystem) joined the stage to host the first Town Hall of the year, almost 6 months after the last one! While on stage, they were joined by various other team members to go over most of the alpha related to the topic at hand:\nSAGE C4 — Danny (CPO) & Brett (VP of Engineering)\nUE5 — Chip (VP of Game Design) & Dominic (Sr. Community Manager)\nHolosim — John (Product Manager) & José (Lead Noot)\nIf you missed the Town Hall and want to watch the full event, then be sure to check out the recording!\nIn addition to the lengthy report below, the team has also composed a shorter summary of the event, which can be found on their Medium account. Note that our report also takes into account some clarifications and extensions provided on Discord and the Economic Forum that took place the following day.\nTLDR\nSAGE — The team shared an incredible amount of details on SAGE C4. It will take a few more months before it makes its way to a public beta-test (PTR), which itself will likely run for a few months. With this release, the team will drop “Labs” from the name; it will simply be called SAGE after launch.\nUE5 — The team shared details about the upcoming July release and the progression ideas they are working on.\nHolosim — The free-to-play version of SAGE is live right now! It comes with a lot of experimental features that may make their way into SAGE at a later point. Examples: Quests, AI chat,\nReport\nSanti kicked off by letting us know that they will spill every bit of information on C4 that they currently have. Additionally, a variety of Atlas Brews in multiple languages will be organized to cover the content of this Town Hall over the coming week.\nMichael takes over to share that after Breakpoint and the Impact meeting, the team came together and asked themselves:\nWhat does a solid 2025 look like for us? What do we want to build? What do we think is going to have the largest impact? And what are the timelines around those things?\nThe team’s philosophy for 2025 is to simplify use onboarding, create great experiences, and reduce the overall barrier to entry.\nSAGE – C4\nThe team consciously decided to extend the timeline for the next feature release of SAGE, allowing them to incorporate more features in one go and make a bigger impact.\nAs a reminder, C4 stands for:\nClaim Stakes\nCombat (systems)\nCouncil Rank\nCrafting Habs\nStar Atas Golden Era – Custom Development Tools\nDanny explains that C4 is where SAGE turns into a full 4X game (eXplore, eXpand, eXploit, eXterminate). He then showcases a new Development Editor Suite that the team has created to develop and maintain the game. These were mostly vibe-coded by Danny. Even the website that hosts them took only about 1 hour to create.\nExpanded Map\nTo kick things off for C4, Danny jumps into the Map Editor he created himself. In there, he shows off the new map for Galia Expanse, which has grown drastically! There will be 315 star systems per Faction (945 in total), though most will be neutral at the start (meaning, not faction-owned). These star systems are all grouped into regions. In total, there are 3656 planets in the new map.\nSAGE C4 Dev Tool – Map Editor\nCurrently, there are 51 star systems that will become Core systems of their own region when C4 launches. Each region will introduce additional star systems, some of which may be Core systems as well. On top of these 51 regions, another brand new 18 regions will be added (6 per faction), resulting in a total of 69 regions with C4. Each system in these regions will come with its own starbase.\nBrett takes over and digs a little deeper.As a faction, to own a region, you need to own all of its Core systems.\nRegions are connected through Warp Lanes (formerly known as Warp Lanes). There is a single warp lane between every two neighboring regions. In fact, these inform the players which regions are considered to be next to one another. This is important, as regions can be divided into safe regions and border regions, and the adjacency of regions determines this.\nSafe Region — If a faction owns this region plus all its neighboring systems, then the region is considered safe. This is an important distinction as these can not be attacked by anyone. Safe regions are safe because they are surrounded by other regions owned by the same faction.\nBorder Region — A region that has at least one neighboring system that is not under the control of the same faction. This could be a neutral system or owned by another faction. In other words, this is a non-safe region.\nOf course, safe regions can become border regions again at a later time, and vice versa. If a border region is lost to another faction, then its adjacent regions will become border regions (if they weren’t already).\nEvery faction has its five regions that are permanently safe because they are in the Safe Zone. Essentially, the creation of additional safe regions expands the safe zone.\nNote that there are still ways to approach attacks tactically. You do not need to attack the front lines solely. You can also fly around and attack a region from behind.\nMovement & Warp Lanes\nYou can still go anywhere on the map through subwarp and warp. However, there is now a third option: Warp Lanes (formerly known as Star Path). When your faction owns two neighboring regions, your fleets can use the warp lane between them.\nSub Warp: unchanged\nWarp: Beyond the cool-down at the end, the team added a delay before warping starts as well, called “spooling”. They did this to make it less easy to escape combat.\nWarp Lanes: If you prefer to pay ATLAS instead of Fuel, and travel a lot faster, you can use a warp lane to jump between regions.\nIt’s good to know that the Atlas fees paid for use of warp lanes will flow to the DAO.\nMiscelaneous\nBrett briefly goes over the resources shown in the Map Editor. There are now:\n86 raw resources\n229 intermediate components\n145 ingredients\nThe final but shared is that Starbase upkeep will be gone. There won’t be a need, or even a possibility, to supply Food or Toolkits to a Starbase.\nThere won’t be a High Risk Zone just yet. It’s all Safe Zone / Low Risk Zone and Medium Risk Zone.\nCombat\nCombat will start in a simplified fashion. It’s not going to be very tactical, let alone like ships flying over each other. It is atomic. Combat happens instantly when a fleet attacks another fleet or starbase. Damage will be dealt in both directions, and that’s it. If both fleets are still standing, they can do it again. The damage dealt is based on the fleet stats and a random factor to make it more interesting and less deterministic. There is no benefit to being the attacker or defender. Also, it’s possible for both fleets to be destroyed in an attack action.\nWhen you blow up a ship, its cargo pod will drop. This contains all of their cargo, and you’ll be able to take a portion of those items. Some of them will get burned when you salvage these, but you’ll still get a portion of those items. Salvage ships will be able to get more of those items, giving them a clear purpose in the game as well.\nGood to know: Loot is locked to the last hitter for a period of time. Afterwards, it’s open to everyone.\nEditor’s note: During the Economic Forum, Chris (VP Game Economy) added that ships will be out of commission for a while after they are blown up as well. However, for a price, you can get these back into action sooner.Additionally, he mentioned that LP will drop upon the destruction of a ship, and like the loot, it will go to the player who dealt the final hit. The amount of LP earned will be substantial compared to other LP-earning activities, such as through Upgrading & Upkeep.\nAction Points & Range\nThe current map contains sectors, but with C4, the team is dropping this and switching to a 64-bit global coordinate system. Every star system, planet, and fleet will have coordinates on this map.\nPreviously, you could interact with everything within your sector and navigate to anything outside of it. Now that sectors are no more, the team defined a global (inter)action range. This is currently set to 0.5 AU, and it applies to all ships, big and small (to keep it simple for the blockchain developers). A fleet can interact with anything within that range, including attacking, repairing, and looting.\nRed: For those wondering, a square/sector in the current game is 1 AU x 1 AU. If you position a fleet in the middle, you would have a pretty good idea of its action range (though it’s a circle, not a square).\nBeyond this action range, there is also a system called Action Points, although this may be abstracted away in the user interface. Every fleet has a number of action points, which can be regarded as an energy bar, that are spent on actions. Some actions deplete all of these, such as performing a repair or when salvaging loot. Other actions only spend some points, such as attacking and defending.\nThis system ensures that a large fleet cannot attack nonstop. It will need to take breaks to restore action points in between.\nTerritory Conquest\nBeyond attacking fleets, Starbases can be attacked as well. Starbases are essentially giant statblocks (lots of defense). An interesting feature is that each tier must be defeated separately. When you defeat a T4 Starbase, it will become Tier 3, for example. You can of course continue attacking to bring it further down, to Tier 2.\nIf you blow up a Tier 1 Starbase, it will become a Tier 0 Starbase for your Faction. If you blow up a T0 Starbase, it will become yours without losing another Tier.\nIf another Faction is upgrading from T0 to T1, you get the Starbase with a portion of these upgrade efforts right away. For example, if the Starbase is 99% on its way to T1, then it will swap factions once defeated, and perhaps it will already be 80% upgraded to T1.\nWhen a Starbase changes hands, any resources in the Starbase are burned (including everything on the local markets, in crafting, storage, etc.).\nRepair\nRepair ships can target ships and star bases. You can pay Toolkits to repair a ship in space or repair a star base. It adds to basically a pending pool. The asset’s health will go up to a certain level based on the toolkits in this pool, but at a certain “healing” rate. So it’s not like an instant repair, but it repairs over time. This means that it can potentially be out-damaged.\nStarbases\nThe idea is that existing Starbase upgrades will be migrated as is to C4 (in other words, the current upgrades will persist). There are several benefits to leveled-up Starbases. Higher-tier Starbases will lower the fee on warp lanes, plus unlock more Claim Stake and Crafting Hab slots. The Starbases also get a higher stat block (including improved defenses).\nDanny chimes in by saying that every region comes with a few Core systems. Owning all Core systems is required to gain ownership of the Region. He is currently contemplating electing one of these Core systems to a so-called King-system. This system is where the local market for that region resides. His idea is that the current Star systems in SAGE Labs would become such King systems.\nSAGE C4 Dev Tool – Ship Configurator\nShip Configuration\nThere are at present 61 ships. You will be able to configure every one of these with custom components in C4, such as components, modules, ship weapons, countermeasures, and missiles. To accomplish this, the team will add ~3,900 recipes to the game, allowing players to craft Tier 1-5 components for each ship and their corresponding component slots. This will include weapons that come in various damage types, such as energy and kinetic weapons.\nHowever, you won’t be able to just apply any one component to any one ship. It’s not fully free-form. Instead, you will be able to build certain sets of components (dubbed: configurations), and then you can apply such a set as a whole only. There will be about 15-20 configs/sets per ship that players can work towards creating, containing both standard sets for each tier, but also sets targeting specific specializations, such as mining.\nIn the future, you will be able to swap components individually, but for C4, they took this shortcut.\nAn upgraded ship won’t become a new NFT. This would fragment the market immensely and really hurt liquidity. The ship will stay (the same NFT) as it is today (decked out with non-weapon T0 components) without extras. How this will work is that when you create a fleet, you choose the ship configurations you want to apply to each ship that you add.\nTo work on these components and their configurations, Danny created an internal Ship Configurator tool that allows the team to configure ships with these components and compare them to each other for balancing.\nAll of these components will have recipes, and they will be craftable solely by players. The team won’t sell these. There will be a process to convert the current Ship Part Bundles into raw resources, which go into crafting these components.\nIf a ship is destroyed, you will lose all components, while the ships will respawn at the CSS.\nMichael chimes in:\n[This is a] massive enhancement to the way that the player economy is going to work because it’s very conceivable that an individual player is not able to craft all of these underlying components that they want to equip on their assets. And then on top of this, when the war machine is rolling and you have combat and you have faction conflict, all of these components are just getting regularly destroyed. And there will be a requirement to rebuild, reconstruct those. And I’m just thinking about the way that that is going to enhance trade and drive peer-to-peer trade and revenue opportunities for players. Absolutely massive as a sink and also as a new way for players to participate in the economy and pick up some revenue by servicing those that require these components.\nThere will be a heavy weighting of LP to combat systems, encouraging those engagements. On that topic, it will be less rewarding for a larger fleet to destroy a smaller one than for a smaller fleet to destroy a larger one.\nClaim Stakes\nTo be able to deploy Claim Stakes, your faction needs to not only own the Star System (Starbase) but also the whole Region as well (which means ownership of all Core systems).\nEach planet in a system owned by your Faction comes with slots where players can deploy Claim Stakes. Within a deployed Claim Stake, its owner can build a variety of buildings (there will be hundreds of different ones). Once a player claims a spot for their Claim Stake, they can start designing the layout and buildings they want in it. Beyond creating and upgrading buildings, buildings can also be replaced with new ones. Given the numerous building options, players will have the opportunity to spend a considerable amount of time designing their perfect base of operations.\nGoing over some building options, Brett briefly elaborates on Mining Drills. When drilling for resources, the richness of a resource multiplies the mining rate linearly (e.g., richness 2 means you would get 2x the output compared to richness 1).\nThere is also a Power resource, which is required by some buildings to function. Power is not an item, instead it can only be generated by buildings within the Claim Stake. There are buildings such as Solar Farms and Power Plants that do this.\nAdditionally, your crew requires accommodations, so you need to construct Barracks. Some of the buildings you can build come with lower crew requirements. In short, optimizing your Claim Stake is an interesting puzzle!\nAutomated Production\nBeyond the extraction of resources, Claim Stakes are also able to do some crafting in an automated fashion, depending on the buildings constructed. This production will, unlike crafting at a Starbase, not incur any crafting fees.\nIn addition, beyond producing resources, your facilities may also require items as input that you are not (sufficiently) able to produce locally, such as Fuel. In these cases, your facilities rely on you transporting these items there.\nRent\nThere is a cost to having a Claim Stake deployed, however. There is a rent players have to pay for each Claim Stake, which is multiplied by the Tier of Starbase and the Tier of Claim Stake. If you run out of rent, there is a grace period where your claim stake stops producing. After it expires, you can be evicted by any other player who wants your spot.\nDestruction\nIf a system changes hands, the buildings on the planets in that system will be destroyed, and the Claim Stakes themselves will respawn at the CSS. If a Starbase loses a Tier (due to being partially destroyed), there will be a reduction in the amount of Claim Stakes of each Tier that the system can facilitate. If you were to have a claim stake in an excess slot, you would lose all buildings, and your Claim Stake would end up at that Starbase.\nExample: There are 200 T1 Claim Stake slots, but due to the Starbase losing a Tier, it goes down to 200. If you are in slot #102, your slot is lost, your Claim Stake is returned to the Starbase, and your buildings are lost.\nMiscelaneous\nYou won’t be able to build Claim Stakes. You can not upgrade Claim Stakes either. The team will sell another tranche of Claim Stakes around the time C4 launches.The recommendation, therefore, is not to go purchase above the original price!\nThere are still asteroids out there to mine with ships. That said, excluding mining ships, all ships, especially Fighter ships, will be significantly downgraded in their mining capability.\nCrafting Habs\nThis will look and behave very similar to Claim Stakes. Players can build these on Starbases instead of on Planets, and like Claim Stakes, they require regular rent payments as well. They do not extract, but have crafting effects. When you craft, you can choose a crafting habit for that craft. The chosen habitat will affect factors such as efficiency, the number of crew required, and fee reductions. There will also be new recipes that can be unlocked by building certain structures within crafting habs.\nGood to know: Crafting habs can only work on a limited set of crafting jobs at a time.\nCouncil Ranks\nThis is the entire progression system for the game. It is used to unlock everything across the game. Beyond the current 4 XP licenses that are in-game right now, C4 will add additional ones, such as for combat and building. Any XP you gained so far (and will still gain before C4 launches) will carry over to the new game.\nYou also earn Renown, which is your overall council rank.\nTo unlock new or expand existing functionality, in-game, you will need to unlock Research Nodes. Some nodes will have dependencies on each other (requiring others to be unlocked first). Unlocking a new research node may cost:\nRenown\nXP\nResources\nResearch nodes will unlock, among other things:\nBuildings\nShip configs\nClaim Stake tiers\nShip size (how big of a ship can you pilot)\nAmount of fleets (how many fleets can you have on a single account)\nNew scanning patterns: They will have different costs, come with different (spawn) maps, and have different resource requirements.\nYou will be able to create fleets regardless of the limitation to use them in-game. This will allow you to rent them out instead.\nSAGE Dev Notion Document – Council Rank & Research\nInfrastructure\nStarComm has undergone a major rewrite to support C4. As Brett put it: “With the basically over 100x-ing of the amount of stuff going on in C4, we really need something that can support that”. It’s now far more scalable. It now consists of a single database that stores the current state, with a couple of servers listening for changes. The servers are live, listening to a stream of data, and each of these servers runs an internal SQLite database, allowing them to execute complex queries. Clients connect to these servers.\nBoth the client code and StarComm code have become a lot simpler as a result. It should therefore perform a lot better than the current version. This new version will roll out with C4.\nStarframe\nSolana’s Anchor framework is great, but to create SAGE, it was not enough. So the team built their own framework, dubbed Starframe. This allowed them to say goodbye to a lot of redundant accounts. Additionally, many accounts have been merged, making them extremely fast to access. The team rewrote SAGE in a couple of weeks on top of Starframe.\nCoherent UI\nThe team has integrated Coherent UI into their Unreal workflow. This allows them to incorporate web code as UI elements in Unreal, which means they can share a wide range of UI elements between Unreal and the web, making everything significantly easier for them. It enables the team to make significantly more progress with significantly less effort.\nRollout\nC4 will be released in a beta state on a Player Test Range/Realm (PTR) on Atlasnet (the team’s internal replica of Solana), where everyone will be able to test it. This will likely run for a couple of months. From there, it will roll out as SAGE (no longer referred to as Labs) afterwards, in-browser. Over the course of the year, the team will also work on a full integration and feature parity in Fleet Command.\nThis will launch on Atlasnet, and testers will likely get a bundle of game assets to play with. Everybody will be able to get access, and playing that beta will not cost anything (no on-chain fees).\nThere are some longer-term implications regarding Atlasnet. The team is preparing for another big Town Hall, where they will discuss Atlasnet and their plans in more detail.\nC4 will come with a new Game ID when it goes live on the mainnet. The team plans to introduce a migration path for the current players.\nMichael shared that it will likely take the team a couple more months before C4 goes live on the PTR.\nStar Atlas – Data Runner Sale\nData Runner Sale\nMichael announces that the team just launched a sale of Data Runners ships, specifically 280 Fimbul BYOS Rangers and 400 Opal Rayfams. They are sold at a 50% discount for a limited time. It will run until Monday of next week, unless sold out earlier.\nUE5\nChip (VP Game Product) and Dominic (Sr. Community Manager) are joining the stage for the UE5 session.\nThe velocity at which the UE5 has been developing has significantly increased this year. The team also chose to release new features more frequently.\nChip will go over the scope of the next major release, which is planned for the middle of the year (Ed: July, it would seem like). It is going to be the next major push into their multiplayer gameplay, including racing. After that, the team will move on to Fleet Command to ensure they reach feature parity with Sage C4 as soon as possible.\nProgression\nThe first focus of the mid-year major release is progression. The team wants to give players a reason to come back. To do this, they are introducing the concept of a pre-season character group rank.\nThe team will split your crew into character groups by both species and gender. So, for instance, High-Punaab males, Sogmian females, or human males. You will progress your character group ranks based on the category the crew member you play with falls within.\nUntil the team implements full-on-chain progression of individual crew cards or members, they want to provide a way for you to still progress at the crew level. And, because they didn’t want to build out a new server infrastructure that is off-chain, they’ve chosen to use Epic Online Services stats. This comes with limitations, such as only tracking ~1,000 stats per account, but it does allow them to track a player’s human male track or their High-Punaab female track..\nBeyond levelling up individual crew members, this is the next best way. So, in short: if you play with a high-Punaab female, any of them that you own, XP that’s earned while playing with them will go towards that group’s track.\nEach track comes with 20 levels, and when you reach level 20, your level will be reset again to 1, but you will have earned a prestige rank. You can prestige like this up to 10 times. You gain XP only by playing matches on dedicated servers. You will be able to get increased XP based on things such as:\nThe rarity of the crew you are playing with\nPlay-streaks (Daily check-ins and consecutive days of play)\nYour prestige level\nStar Atlas – Designs for UE5\nProgression Rewards\nIn-game, jetpacks are called jetties, and shields are called bubby’s. Characters come with three different slots in-game, including a jettie hand slot, a jettie sole slot, and a bubby slot. You’ll be able to unlock different variants of those equipables as you level up a character group rank.\nThe plan is to get on-chain rewards as well! At certain leveling thresholds, you will likely get a crewpack airdropped, which may be a special version/tier of the crew packs we all know and love. The team is also looking into rewarding an exclusive UE5 type of resource, likely the nano bots, which would then become a requirement in certain C4 recipes. This will introduce some economic crossovers between UE5 gameplay and the C4 Sage economy.\nStar Atlas – UE5 Progression Level Rewards\nAs you start at level 1, you have a total of 4 weapon slots. Different weapons take up different amounts of slots. Your default equipment, including your Kinetic Pistol and Kinetic Auto Rifle, will take up three slots. At level 2, you unlock a starter grenade, which costs another slot. At level 3, you unlock a sole jettie, allowing you to dash and slide at a lower cost, but perhaps it has less speed for hovering. The goal is to ensure every new item has some trade-offs as well, preventing them from easily becoming the most dominant item in-game. You will continue to unlock weapons, jetpack slots, and weapon slots. Refer to the table above for more information on the rewards currently planned.\nIf players prefer to play a match outside of this progression system, they can toggle this mode off in the match settings. If they do, weapons will still spawn on the map as they do today. If they, however, opt for this progression game mode, those weapon spawns will be replaced by ammo packs instead. Weapons will then have to be earned.\nThe team is also working on persistent regional dedicated server lobbies. These will be the XP-enabled ones, and they will feature rotating game modes on a weekly basis.\nWhen you prestige from level 20 to level 1, you keep everything you unlocked. You may unlock new benefits at, for example, prestige 2, level 5.\nChip stresses that this is not solely focused on their gunplay mode right now. They are instead building out foundational game systems that the team wants to use in their open-world game mode as well. Perhaps you will be able to have 30 weapon slots in that mode, but the same principles will hold. They have not shifted focus to these repeatable arena shooters.\nOther Improvements\nNext, he is showcasing concepts for a redesigned scoreboard that will provide more detailed, up-to-date statistics for a wider range of players. This is in response to players complaining about the current scoreboard. Additionally, there will also be assists registered there now as well (for team players).\nChip then jumps in-game to perform a live demo of some July updates.\nOne of the unique selling points of the shooter the team built is its distinctive movement, which incorporates jetpacks and related movement features. The team is going to lean even more into momentum preservation (something Chip shows off).\nAdditionally, the team revised the impulse around sliding. It is faster and more fluid. It feels better, and there will be jetty variants that will alter it.\nIn general, movement just feels better with ending hover and jettie boost. Furthermore, sliding is improved, and bunny hopping was added.\nAdditional features planned:\nIntegration of Easy Anti Cheat\nAddition of a Spectator mode\nPolishing Paizul’s Arena to completion. The crowds will throw confetti and trash at you. More detail will be added to the map (e.g., moss, water) and soundscape (the ships flying around emit sounds as well). The team wants to show off to what level of fidelity they can really build their environment.\nReplacing race track B with a Sogmian-themed track called Exonade.\nRefreshing the main menu (making it more compelling)\nImproving joystick & gamepad support (showing a clip of Brad playing with a Joystick/HOTAS setup)\nTo close out the UE5 segment, Chip has something cool to show us!\nThe team decided to prototype another career path in Galia, beyond mining, namely scanning. The team shows a video demonstrating scanning in UE5. Brad is scanning, and he has found a distress signal. As he gets closer, more details are provided. It looks like a mini-quest where the player is asked to provide assistance. Audio plays when Brad approaches the ship in distress. There is some fun banter going on between the couple that resides on the ship, but after a short while, they get jumped by Jorvik pirates.\nWhen Brad saves the ship, he gets some credits as a reward.\nBrad has created several of these mini-quests already (also writing the scripts and facilitating the voice acting).\nStar Atlas – Holosim\nHolosim\nThe Holosim is themed as an actual in-game “game” simulation running on Atlasnet. As Michael put it: “It is our full free-to-play simulated universe implementation of the Sage feature set.”\nBeyond being a free-to-play variant of SAGE, however, it comes with numerous new features (not yet available in SAGE).\nHolosim is meant to facilitate user acquisition and lower the threshold for new players. Michael shared:\n[…] in order for us to achieve success and to truly see the fruits of all of the labor here blossom, it’s important for us to grow the user base, the community, the ecosystem substantially.\nThe team recognizes that SAGE has a steep learning curve and a significant cost of entry. And UE5 is still at a very early stage. Fortunately, Jacob (CTO & co-founder) had started work on a free-to-play product in his spare time. He largely vibe-coded an early version of Holosim in evenings and weekends at first, with some team members jumping in to help. All in all, very few resources have been required to create this version of the game.\nThe goal was, first and foremost, to create a fun and engaging experience. As it does not have the benefits of a live, real cash economy like Sage, fun had to be #1. It also comes with zero barrier to entry. All on-chain actions happen invisibly in the background, including wallet creation. There is no asset requirement either, completely eliminating the barrier to Play.\nThis also makes it much easier to port to mobile. It may become a stand-alone app on the iOS and Android stores, and the team actually has this on their roadmap!\nBy eliminating those friction points, the team hopes to capture a Web2 audience. There are tutorial systems that, in the end, also explain how SAGE works. Holosim teaches them how to play SAGE without any monetary risk.\nAdditionally, Holosim also allows the team to introduce new features that the team can experiment with. It’s sort of a test environment for the team. It also allows the team to create new sources of monetization, perhaps with battle passes or such.\nXcode and José have joined the stage.\nJosé takes over from Michael. He starts by explaining that Holosim is a space for the team to experiment and go wild.\nIt is a simulator of realities in Star Atlas. There will be seasons, and every season will be based on a scenario with a specific set of rules. The players will compete according to the rules of that season and try to perform across the leaderboards.\nSeasons could alter game rules drastically, even merging factions into one to fight HRZ threats.\nHolosim – UI\nFor this early release, there will be a race between factions. In every faction, every player is competing to fulfill faction contracts of different types all across the star systems in Galia.\nIt seems simple, but appearances are deceiving. Holosim comes with a quest system, allowing players to specialize in 4 different careers (Soldier, Data Runner, Miner, Merchant). You choose a single specialization, and will then start to unlock recipes in that tab. Every specialization is required to fulfill parts of the game.\nIf you become a soldier, you will be able to craft certain combat-focused ships. Each specialization will excel at its own gameplay loops.\nShips are very different from SAGE ships. Their specialization stats will be far better. The game is designed to highlight differences between ships.\nHolosim – Chat\nThere is chat as well! Players need to communicate to achieve the faction objectives and excel on the leaderboard.\nHolosim comes with an AI chat buddy, intended to be your ship’s computer. She will help you go through the game and perform in the best way possible.\nFinally, there is combat! Combat (v0) allows you to attack other fleets. In this season, combat is High Risk! If you lose, your ships are gone, along with your crew members.\nHolosim is based on the delivery of contracts. If you defeat a fleet carrying those contracts, they can be looted and used for your faction’s benefit.\nMiners need to craft the contracts, merchants need to haul them and provide liquidity and resources, data runners acquire SDUs and craft data contracts, and soldiers will defend their fellow crew members and steal contracts from the opponent.\nYou can be ambushed while in subwarp. You can not be attacked when warping. Jose shows how he destroys one of John’s fleets in 3 hits (or actually, it seems to have fled with 1 hp left). If a subwarping fleet leaves the sector, then combat will end.\nHolosim – Combat example\nAfter warp, there will be a cooldown before you can dock with Starbases to make fleets a little more vulnerable.\nThere are Quests to help introduce new players to the game.\nHolosim – Quests\nAll quests come with (AI-generated) narration plus text. There are 72 quests for this first version, taking players from forming their first fleet all the way to creating a Titan ship.\nThe redemption of all contracts in the MRZ is the end-game condition for this first season, and that may happen before a player gets to craft a titan.\nSome more details:\nEvery fleet you form can be given basic instructions when docking. Example: Every time this fleet docks, it should refuel, rearm, supply some food, and unload its cargo. As there are no transaction costs, this made sense for the team to implement here.\nAt level 5, you unlock the Fleet Route Manager. Choose between mining or transport loop, select a fleet, and select a location, and the fleet will automatically start performing this task continuously.\nEverybody starts with 21 crew. You receive a daily airdrop of an additional 21 crew members if you complete the daily quest check-in (these numbers may change).\nYou need fewer crew than you would need on the mainnet, but they will die when on a fleet that is destroyed. Crew are the most precious resource in Holosim.\nPower levels are roughly 3:1 (3 mediums are a match for 1 large fighter, but the large fighter has an advantage).\nSubwarp is slow. Warp cooldowns are reduced. Warp ranges are a little less as well. If you want to loot cargo, you need to bring a transport ship.\nYou’ll get the majority of your XP through questing and following the storyline. Your level gates the resources and recipes you have access to in-game. Loosely, the Tiers line up with the level you need. See the Crafting Level Progression table below.\nYou need a very recent browser to play the game.\nWarning: Clearing cache and cookies will eliminate your game and all progress. This is where your Atlasnet wallet lives!\nThis is a meta game that exists in Star Atlas. Players will (down the line!) be able to play the holosim directly from within Fleet Command as well.\nLevel\nUnlock\n0\nEssential mining and survival materials\n1\nBasic ship components and fuel systems\n5\n(X)XS Ship crafting & Basic Contracts\n10\nSmall Ship Crafting\n15\nMRZ Contracts\n20\nMedium Ships\n25\nHRZ Contracts\n30\nLarge Ships\n35\nData/Crystals Contracts\n40\nCapital Ships\n50\nCommander Ships\n61\nMUD/ONI/Ustur Infrastructure Contracts\nCrafting Level Progression\nHolosim has launched! It is live!\nTurned out that John was demoing on the live server the whole time: https://holosim.staratlas.com.\nThe plan is to provide some rewards, but they are not yet out on which ones exactly. It could be a mainnet welcome bundle for SAGE. Converting users to mainnet is definitely something the team is looking into.\nThat is a wrap!",
  "entities": [],
  "events": [],
  "claims": [],
  "quotes": [],
  "relationships": [],
  "products": [],
  "governance_items": [],
  "guilds": [],
  "actors": [],
  "lore_items": [],
  "dates": [
    "2025"
  ],
  "external_sources": [
    "https://aephia.com/star-atlas/town-hall-report-december-18-2024/\"",
    "https://aephia.com/wp-content/uploads/2025/06/DataRunner_June4-1024x1024.png",
    "https://aephia.com/wp-content/uploads/2025/06/DataRunner_June4-1024x1024.png\"",
    "https://aephia.com/wp-content/uploads/2025/06/DataRunner_June4-1320x1320.png",
    "https://aephia.com/wp-content/uploads/2025/06/DataRunner_June4-150x150.png",
    "https://aephia.com/wp-content/uploads/2025/06/DataRunner_June4-1536x1536.png",
    "https://aephia.com/wp-content/uploads/2025/06/DataRunner_June4-2048x2048.png",
    "https://aephia.com/wp-content/uploads/2025/06/DataRunner_June4-300x300.png",
    "https://aephia.com/wp-content/uploads/2025/06/DataRunner_June4-768x768.png",
    "https://aephia.com/wp-content/uploads/2025/06/Screenshot-2025-06-04-at-20.26.28-1024x641.png",
    "https://aephia.com/wp-content/uploads/2025/06/Screenshot-2025-06-04-at-20.26.28-1024x641.png\"",
    "https://aephia.com/wp-content/uploads/2025/06/Screenshot-2025-06-04-at-20.26.28-300x188.png",
    "https://aephia.com/wp-content/uploads/2025/06/Screenshot-2025-06-04-at-20.26.28-768x481.png",
    "https://aephia.com/wp-content/uploads/2025/06/Screenshot-2025-06-04-at-20.26.28.png",
    "https://aephia.com/wp-content/uploads/2025/06/Screenshot-2025-06-04-at-20.28.36-1024x640.png",
    "https://aephia.com/wp-content/uploads/2025/06/Screenshot-2025-06-04-at-20.28.36-1024x640.png\"",
    "https://aephia.com/wp-content/uploads/2025/06/Screenshot-2025-06-04-at-20.28.36-300x188.png",
    "https://aephia.com/wp-content/uploads/2025/06/Screenshot-2025-06-04-at-20.28.36-768x480.png",
    "https://aephia.com/wp-content/uploads/2025/06/Screenshot-2025-06-04-at-20.28.36.png",
    "https://aephia.com/wp-content/uploads/2025/06/Screenshot-2025-06-04-at-20.29.42-1024x642.png",
    "https://aephia.com/wp-content/uploads/2025/06/Screenshot-2025-06-04-at-20.29.42-1024x642.png\"",
    "https://aephia.com/wp-content/uploads/2025/06/Screenshot-2025-06-04-at-20.29.42-1320x828.png",
    "https://aephia.com/wp-content/uploads/2025/06/Screenshot-2025-06-04-at-20.29.42-1536x964.png",
    "https://aephia.com/wp-content/uploads/2025/06/Screenshot-2025-06-04-at-20.29.42-300x188.png",
    "https://aephia.com/wp-content/uploads/2025/06/Screenshot-2025-06-04-at-20.29.42-768x482.png",
    "https://aephia.com/wp-content/uploads/2025/06/Screenshot-2025-06-04-at-20.29.42.png",
    "https://aephia.com/wp-content/uploads/2025/06/Screenshot-2025-06-04-at-20.48.28-1024x641.png",
    "https://aephia.com/wp-content/uploads/2025/06/Screenshot-2025-06-04-at-20.48.28-1024x641.png\"",
    "https://aephia.com/wp-content/uploads/2025/06/Screenshot-2025-06-04-at-20.48.28-300x188.png",
    "https://aephia.com/wp-content/uploads/2025/06/Screenshot-2025-06-04-at-20.48.28-768x481.png",
    "https://aephia.com/wp-content/uploads/2025/06/Screenshot-2025-06-04-at-20.48.28.png",
    "https://aephia.com/wp-content/uploads/2025/06/Screenshot-2025-06-04-at-21.32.37-1024x482.png",
    "https://aephia.com/wp-content/uploads/2025/06/Screenshot-2025-06-04-at-21.32.37-1024x482.png\"",
    "https://aephia.com/wp-content/uploads/2025/06/Screenshot-2025-06-04-at-21.32.37-300x141.png",
    "https://aephia.com/wp-content/uploads/2025/06/Screenshot-2025-06-04-at-21.32.37-768x361.png",
    "https://aephia.com/wp-content/uploads/2025/06/Screenshot-2025-06-04-at-21.32.37.png",
    "https://aephia.com/wp-content/uploads/2025/06/Screenshot-2025-06-04-at-21.57.40-1024x577.png",
    "https://aephia.com/wp-content/uploads/2025/06/Screenshot-2025-06-04-at-21.57.40-1024x577.png\"",
    "https://aephia.com/wp-content/uploads/2025/06/Screenshot-2025-06-04-at-21.57.40-1320x744.png",
    "https://aephia.com/wp-content/uploads/2025/06/Screenshot-2025-06-04-at-21.57.40-300x169.png",
    "https://aephia.com/wp-content/uploads/2025/06/Screenshot-2025-06-04-at-21.57.40-768x433.png",
    "https://aephia.com/wp-content/uploads/2025/06/Screenshot-2025-06-04-at-21.57.40.png",
    "https://aephia.com/wp-content/uploads/2025/06/Screenshot-2025-06-04-at-21.58.57-300x171.png",
    "https://aephia.com/wp-content/uploads/2025/06/Screenshot-2025-06-04-at-21.58.57-768x439.png",
    "https://aephia.com/wp-content/uploads/2025/06/Screenshot-2025-06-04-at-21.58.57.png",
    "https://aephia.com/wp-content/uploads/2025/06/Screenshot-2025-06-04-at-21.58.57.png\"",
    "https://aephia.com/wp-content/uploads/2025/06/Screenshot-2025-06-04-at-22.02.19-275x300.png",
    "https://aephia.com/wp-content/uploads/2025/06/Screenshot-2025-06-04-at-22.02.19.png",
    "https://aephia.com/wp-content/uploads/2025/06/Screenshot-2025-06-04-at-22.02.19.png\"",
    "https://aephia.com/wp-content/uploads/2025/06/Screenshot-2025-06-04-at-22.41.39-300x269.png",
    "https://aephia.com/wp-content/uploads/2025/06/Screenshot-2025-06-04-at-22.41.39.png",
    "https://aephia.com/wp-content/uploads/2025/06/Screenshot-2025-06-04-at-22.41.39.png\"",
    "https://aephia.com/wp-content/uploads/2025/06/Screenshot-2025-06-04-at-22.43.40-150x150.png",
    "https://aephia.com/wp-content/uploads/2025/06/Screenshot-2025-06-04-at-22.43.40-298x300.png",
    "https://aephia.com/wp-content/uploads/2025/06/Screenshot-2025-06-04-at-22.43.40.png",
    "https://aephia.com/wp-content/uploads/2025/06/Screenshot-2025-06-04-at-22.43.40.png\"",
    "https://aephia.com/wp-content/uploads/2025/06/Screenshot-2025-06-04-at-22.50.36-300x101.png",
    "https://aephia.com/wp-content/uploads/2025/06/Screenshot-2025-06-04-at-22.50.36-768x258.png",
    "https://aephia.com/wp-content/uploads/2025/06/Screenshot-2025-06-04-at-22.50.36.png",
    "https://aephia.com/wp-content/uploads/2025/06/Screenshot-2025-06-04-at-22.50.36.png\"",
    "https://aephia.com/wp-content/uploads/2025/06/Screenshot-2025-06-04-at-23.20.11-150x150.png",
    "https://aephia.com/wp-content/uploads/2025/06/Screenshot-2025-06-04-at-23.20.11-300x300.png",
    "https://aephia.com/wp-content/uploads/2025/06/Screenshot-2025-06-04-at-23.20.11-768x771.png",
    "https://aephia.com/wp-content/uploads/2025/06/Screenshot-2025-06-04-at-23.20.11.png",
    "https://aephia.com/wp-content/uploads/2025/06/Screenshot-2025-06-04-at-23.20.11.png\"",
    "https://aephia.com/wp-content/uploads/2025/06/image-1-1024x1024.png",
    "https://aephia.com/wp-content/uploads/2025/06/image-1-1024x1024.png\"",
    "https://aephia.com/wp-content/uploads/2025/06/image-1-1320x1320.png",
    "https://aephia.com/wp-content/uploads/2025/06/image-1-150x150.png",
    "https://aephia.com/wp-content/uploads/2025/06/image-1-1536x1536.png",
    "https://aephia.com/wp-content/uploads/2025/06/image-1-300x300.png",
    "https://aephia.com/wp-content/uploads/2025/06/image-1-768x768.png",
    "https://aephia.com/wp-content/uploads/2025/06/image-1.png",
    "https://coherent-labs.com/Documentation/cpp/\"",
    "https://holosim.staratlas.com",
    "https://holosim.staratlas.com/\"",
    "https://medium.com/star-atlas/star-atlas-town-hall-recap-the-new-web3-era-is-upon-us-faa04d92ca6f\"",
    "https://www.youtube.com/live/OxbO8m7H4C8?si=6zeCfEmU390ZikOn\"",
    "https://www.youtube.com/live/OxbO8m7H4C8?si=iJrY7kK8k50tbVt4\"",
    "https://www.youtube.com/live/ZritNok3f3A?si=CntNpNFB2lGnJPC5\""
  ],
  "open_questions": [],
  "temporal_status": "HISTORICAL_SNAPSHOT",
  "current_validity": "REQUIRES_RECONCILIATION",
  "quality": {
    "extraction_confidence": "HIGH",
    "date_confidence": "HIGH",
    "author_confidence": "MEDIUM",
    "completeness": "COMPLETE",
    "manual_review_reasons": [
      "Article was modified after publication; review temporal claims against later evidence."
    ]
  },
  "retrieval": {
    "http_status": 200,
    "final_url": "https://aephia.com/wp-json/wp/v2/posts?slug=town-hall-report-june-4-2025&_fields=id%2Clink%2Cslug%2Cdate%2Cmodified%2Ctitle%2Ccontent%2Cexcerpt%2Cauthor",
    "content_type": "application/json; charset=UTF-8",
    "response_size": 63812,
    "elapsed_ms": 722
  }
}
