{
  "aliases": [
    "MRZ-24"
  ],
  "authority_scope": "OPERATOR_DESIGNATED_LORE_TAXONOMY_AND_NOMENCLATURE",
  "canonical_url": "https://joseeduardonoot.github.io/star-atlas-lore/geography/sectors/vega_fall/",
  "claim_authority": "SOURCE_ASSERTION_REQUIRES_INDEPENDENT_EVIDENCE_FOR_PROMOTION",
  "extraction_confidence": "HIGH",
  "headings": [
    {
      "level": 1,
      "line": 1,
      "text": "Vega Fall (MRZ-24)"
    },
    {
      "level": 2,
      "line": 8,
      "text": "Overview"
    },
    {
      "level": 2,
      "line": 14,
      "text": "The Rise of Vega"
    },
    {
      "level": 3,
      "line": 16,
      "text": "The Luminous Gem"
    },
    {
      "level": 3,
      "line": 24,
      "text": "The Consolidation"
    },
    {
      "level": 2,
      "line": 32,
      "text": "The Fall"
    },
    {
      "level": 3,
      "line": 34,
      "text": "The Exposé: \"Vega Fall\""
    },
    {
      "level": 3,
      "line": 40,
      "text": "The Civil War"
    },
    {
      "level": 2,
      "line": 49,
      "text": "Current State"
    },
    {
      "level": 3,
      "line": 51,
      "text": "House Lutavira Headquarters"
    },
    {
      "level": 3,
      "line": 59,
      "text": "Cultural Significance"
    },
    {
      "level": 3,
      "line": 66,
      "text": "Post-War Refuge"
    },
    {
      "level": 3,
      "line": 70,
      "text": "The Akalma Exile's End (~2544)"
    },
    {
      "level": 3,
      "line": 77,
      "text": "Multi-Species Prosperity (~2586)"
    },
    {
      "level": 2,
      "line": 84,
      "text": "Narrative Hooks"
    },
    {
      "level": 2,
      "line": 93,
      "text": "Cross-References"
    }
  ],
  "internal_links": [],
  "limitations": [
    "Authority is limited to operator-designated lore taxonomy and preferred nomenclature; narrative claims are not independently verified by ingestion.",
    "The upstream repository is publicly hosted but no repository license was declared at capture time.",
    "The published docs mirror differs from the canon authoring page and requires source-level reconciliation."
  ],
  "lore_type": "SECTOR",
  "manual_review_required": true,
  "media_references": [],
  "normalized_json_path": "archive/normalized/lore/pages/SRC-LORE-REPO-E75738A2439A.json",
  "normalized_markdown_path": "archive/normalized/lore/pages/SRC-LORE-REPO-E75738A2439A.md",
  "normalized_sha256": "2363202f8b1e44bedde7faa27b8d171e2364429fe7c3b68f12932f34fc43281f",
  "outbound_links": [],
  "preferred_name": "Vega Fall (MRZ-24)",
  "primary_entity_id": "LRTX-SECTOR-E4DA79DBE8E0",
  "provenance": {
    "captured_at": "2026-07-19T15:26:28Z",
    "snapshot_member": "star-atlas-lore-22555f277eb1496e34c0839c8f1f382842bd1d2b/canon/geography/sectors/vega_fall.md",
    "snapshot_path": "archive/raw/lore-repository/star-atlas-lore-22555f277eb1496e34c0839c8f1f382842bd1d2b.zip",
    "snapshot_sha256": "08061a661f47a8d55d233a79ba5cdadbbd98c471f50b171d2d56ea583f2a04a1"
  },
  "published_mirror_path": "docs/geography/sectors/vega_fall.md",
  "published_mirror_status": "TEXT_DIVERGENT",
  "raw_byte_length": 4488,
  "raw_sha256": "2363202f8b1e44bedde7faa27b8d171e2364429fe7c3b68f12932f34fc43281f",
  "repository_entity_type": "LOCATION",
  "source_id": "SRC-LORE-REPO-E75738A2439A",
  "source_scope": "CANON",
  "taxonomy_path": [
    "geography",
    "sectors"
  ],
  "upstream_commit": "22555f277eb1496e34c0839c8f1f382842bd1d2b",
  "upstream_path": "canon/geography/sectors/vega_fall.md",
  "upstream_repository": "JoseEduardonoot/star-atlas-lore"
}
