{
  "source": {
    "source_id": "SRC-HNN-5999927A64ACCAA5",
    "url_id": "URL-5999927A64ACCAA5",
    "url": "https://medium.com/the-hologram/former-star-atlas-cro-speak-on-departure-eb37dc95ff3",
    "title": "Former Star Atlas CRO Speaks on Departure",
    "author": "Krigs",
    "publisher": "The Hologram",
    "publication_identity": "The Hologram (Medium publication)",
    "published_at": "2023-05-17T18:33:54Z",
    "updated_at": "2023-05-17T18:34:04Z",
    "retrieved_at": "2026-07-13T00:07:58.797949Z",
    "document_type": "REFERENCE",
    "source_role": "REFERENCE",
    "publication_role": "REFERENCE",
    "classification_rationale": "Publication is structured as a guide or reference."
  },
  "source_lineage": {
    "publication": "The Hologram (Medium publication)",
    "publication_role": "REFERENCE",
    "relationship": "REFERENCES",
    "primary_sources": [
      {
        "publication": "Podcast",
        "author": "UNKNOWN",
        "url": "https://open.spotify.com/show/2mxndrDW6yPfpS350ijzjt?si=ec7c717f998240d6",
        "organization": "UNKNOWN",
        "evidence": "Directly linked and named in the publication."
      },
      {
        "publication": "YouTube",
        "author": "UNKNOWN",
        "url": "https://www.youtube.com/channel/UCDa-YxgNG6A9xpH1qyP0OaQ",
        "organization": "UNKNOWN",
        "evidence": "Directly linked and named in the publication."
      },
      {
        "publication": "Star Atlas",
        "author": "UNKNOWN",
        "url": "https://staratlas.com/",
        "organization": "UNKNOWN",
        "evidence": "Directly linked and named in the publication."
      }
    ],
    "original_creators": [
      "Krigs"
    ],
    "attribution_chain": [
      {
        "from": "Podcast",
        "to": "The Hologram (Medium publication)",
        "relationship": "REFERENCES",
        "url": "https://open.spotify.com/show/2mxndrDW6yPfpS350ijzjt?si=ec7c717f998240d6"
      },
      {
        "from": "YouTube",
        "to": "The Hologram (Medium publication)",
        "relationship": "REFERENCES",
        "url": "https://www.youtube.com/channel/UCDa-YxgNG6A9xpH1qyP0OaQ"
      },
      {
        "from": "Star Atlas",
        "to": "The Hologram (Medium publication)",
        "relationship": "REFERENCES",
        "url": "https://staratlas.com/"
      }
    ],
    "lineage_confidence": "HIGH"
  },
  "summary": {
    "archival_abstract": "This reference published by The Hologram on 2023-05-17 documents “Former Star Atlas CRO Speaks on Departure.” Its surviving text addresses economy, game development, community, lore. The record is preserved as contemporary evidence of how HNN presented the subject at publication time; factual and forward-looking claims remain attributed to the publication and require reconciliation with primary or later sources.",
    "historical_value": "Preserves the HNN publication as contemporary community journalism and evidence of the network's editorial record.",
    "current_validity_warning": "Claims reflect the publication date and may have been superseded, corrected, or disproven."
  },
  "article_text": "Star Atlas\nFormer Star Atlas CRO Speaks on Departure\nKrigs3 min read·May 17, 2023\n--\nListen\nShare\nIn his first official comment since his departure from ATMTA, former Star Atlas Chief Revenue Officer Pablo Quiroga speaks on his time with the company.\nDear Star Atlas Community, I hope this message finds you all in good spirits as we embark on the next chapter of our journey together. It is with mixed emotions that I write to you today, for it is time for me to officially address the departure from my role as CRO at ATMTA.\nThis situation was not easy, but it is one that I believe is necessary.\nFirst and foremost, I want to express my deepest gratitude to each and every one of you. The passion and dedication you have shown in building Star Atlas into what it is today is truly awe-inspiring.\nYour commitment to the vision of a decentralized metaverse and your tireless efforts to push the boundaries of what is possible have made this project a force to be reckoned with.\nAs I reflect on our journey together, I am filled with immense pride. We have come so far, overcoming obstacles and challenges that seemed insurmountable. But true progress is not measured solely by the distance traveled; it is also marked by the willingness to adapt and evolve.\nThis is a project that has the opportunity to revolutionize the way we interact, create, and transact within virtual worlds. It is a vision that transcends borders, cultures, and limitations. And it is a vision that will endure, regardless of who is at the helm.\nI have always believed that the true strength of a visionary lies in their ability to inspire others to dream, create, and achieve greatness. And it is my hope that I have been able to ignite that spark within each and every one of you.\nThe legacy of Star Atlas is not tied to any one individual; it is a collective endeavor that belongs to all of us. It is a testament to the power of community, collaboration, and shared purpose.\nI implore you to continue pushing the boundaries of what is possible. Embrace change, for it is the catalyst for growth and innovation. Cherish the relationships you have built within this community, for they are the foundation upon which Star Atlas stands.\nAnd above all else, never lose sight of the awe-inspiring potential that lies within each and every one of you.\nBe light, Pablo\n— Pablo Quiroga, former Chief Revenue Officer of ATMTA, Star Atlas game developer\nQuiroa Speaks After Departure\nQuiroga’s tenure as the Chief Revnue Officer of ATMTA officially ended on March 31st, 2023. However, the official public announcement was made on April, 7th by CEO Michael Wagner. Quiroga, along with Wagner, was among the four founders of Star Atlas.\nQuiroga’s public comments did not address previously reported allegations of workplace grievances or internal creative differences amongst the team. Quiroga’s message was addressed to the Star Atlas community, which have been long supporters of both Quiroga and Star Atlas.\nHis message embraced a harmonic tone and spoke to the testament of the power of the (Star Atlas) community.\nIt remains unclear the reasoning behind Quiroga’s sudden departure from ATMTA. Other than the official comment by Wagner, ATMTA has declined to comment further on the matter.\nAbout the Author\nKrigs is a pioneer in the world of Star Atlas, having founded The Hologram News Network — an independent meta-news organization that keeps players up to date on all developments regarding Star Atlas. An ardent supporter of emerging technologies, Krigs has been covering this game for over a year and believes passionately in their power to revolutionize our collective gaming experience.\nFollow on Social Media:\nPodcast | YouTube | Twitter | Instagram | Web\nAbout The Hologram\nThe Hologram is Star Atlas’ first and only independent news network. Our vision is to become the most trusted source of information about Star Atlas and a voice for the whole community. Readers can expect a high standard from our reporting and staff. Our promise to you: we will not publish anything that hasn’t been thoroughly researched and based on the best facts available.\nThe Hologram is not endorsed or paid by the Star Atlas team. Any information published by The Hologram nor its writers should be considered as informational in nature and does not constitute any financial advice.",
  "content_hash": "a6917d1fa2727846b497c9c9feefe33f2a967a49ecbd959212ca9ed324de0335",
  "major_topics": [
    "economy",
    "game development",
    "community",
    "lore"
  ],
  "entities": [
    "ATLAS",
    "Krigs",
    "Michael Wagner",
    "Pablo Quiroga",
    "Star Atlas"
  ],
  "events": [],
  "claims": [
    {
      "claim_id": "CLM-5999927A64ACCAA5-01",
      "text": "And it is a vision that will endure, regardless of who is at the helm.",
      "claim_type": "RETROSPECTIVE_CLAIM",
      "speaker": "UNKNOWN",
      "reported_by": "Hologram News Network (HNN)",
      "source_id": "SRC-HNN-5999927A64ACCAA5",
      "confidence": "LOW",
      "requires_follow_up": true
    },
    {
      "claim_id": "CLM-5999927A64ACCAA5-02",
      "text": "Quiroga’s public comments did not address previously reported allegations of workplace grievances or internal creative differences amongst the team.",
      "claim_type": "RETROSPECTIVE_CLAIM",
      "speaker": "UNKNOWN",
      "reported_by": "Hologram News Network (HNN)",
      "source_id": "SRC-HNN-5999927A64ACCAA5",
      "confidence": "LOW",
      "requires_follow_up": true
    },
    {
      "claim_id": "CLM-5999927A64ACCAA5-03",
      "text": "Our promise to you: we will not publish anything that hasn’t been thoroughly researched and based on the best facts available.",
      "claim_type": "RETROSPECTIVE_CLAIM",
      "speaker": "UNKNOWN",
      "reported_by": "Hologram News Network (HNN)",
      "source_id": "SRC-HNN-5999927A64ACCAA5",
      "confidence": "LOW",
      "requires_follow_up": true
    }
  ],
  "quotes": [],
  "relationships": [],
  "products": [
    "Star Atlas",
    "ATLAS"
  ],
  "governance_items": [],
  "lore_items": [
    "ONI"
  ],
  "actors": [
    "Michael Wagner",
    "Krigs",
    "Pablo Quiroga"
  ],
  "guilds": [],
  "external_sources": [
    {
      "url": "https://medium.com/@krigsfoniks?source=---byline--eb37dc95ff3---------------------------------------",
      "anchor_text": ""
    },
    {
      "url": "https://medium.com/m/signin?actionUrl=https%3A%2F%2Fmedium.com%2F_%2Fvote%2Fthe-hologram%2Feb37dc95ff3&operation=register&redirect=https%3A%2F%2Fmedium.com%2Fthe-hologram%2Fformer-star-atlas-cro-speak-on-departure-eb37dc95ff3&user=Krigs&userId=41e0c5b141f1&source=---header_actions--eb37dc95ff3---------------------clap_footer------------------",
      "anchor_text": ""
    },
    {
      "url": "https://medium.com/m/signin?actionUrl=https%3A%2F%2Fmedium.com%2F_%2Frepost%2Fp%2Feb37dc95ff3&operation=register&redirect=https%3A%2F%2Fmedium.com%2Fthe-hologram%2Fformer-star-atlas-cro-speak-on-departure-eb37dc95ff3&user=Krigs&userId=41e0c5b141f1&source=---header_actions--eb37dc95ff3---------------------repost_header------------------",
      "anchor_text": ""
    },
    {
      "url": "https://medium.com/m/signin?actionUrl=https%3A%2F%2Fmedium.com%2F_%2Fbookmark%2Fp%2Feb37dc95ff3&operation=register&redirect=https%3A%2F%2Fmedium.com%2Fthe-hologram%2Fformer-star-atlas-cro-speak-on-departure-eb37dc95ff3&source=---header_actions--eb37dc95ff3---------------------bookmark_footer------------------",
      "anchor_text": ""
    },
    {
      "url": "https://medium.com/m/signin?actionUrl=https%3A%2F%2Fmedium.com%2Fplans%3Fdimension%3Dpost_audio_button%26postId%3Deb37dc95ff3&operation=register&redirect=https%3A%2F%2Fmedium.com%2Fthe-hologram%2Fformer-star-atlas-cro-speak-on-departure-eb37dc95ff3&source=---header_actions--eb37dc95ff3---------------------post_audio_button------------------",
      "anchor_text": "Listen"
    },
    {
      "url": "https://medium.com/u/5ed69ff9cfb0?source=---user_mention--eb37dc95ff3---------------------------------------",
      "anchor_text": "Star Atlas"
    },
    {
      "url": "https://medium.com/the-hologram/atmta-employees-speak-on-quiroga-departure-fd8197c23ca1",
      "anchor_text": "announcement"
    },
    {
      "url": "https://medium.com/the-hologram/atmta-insider-spills-on-quiroga-departure-e76045f906d8",
      "anchor_text": "the reasoning behind Quiroga’s sudden departure"
    },
    {
      "url": "https://medium.com/u/41e0c5b141f1",
      "anchor_text": "Krigs"
    },
    {
      "url": "https://open.spotify.com/show/2mxndrDW6yPfpS350ijzjt?si=ec7c717f998240d6",
      "anchor_text": "Podcast"
    },
    {
      "url": "https://www.youtube.com/channel/UCDa-YxgNG6A9xpH1qyP0OaQ",
      "anchor_text": "YouTube"
    },
    {
      "url": "https://twitter.com/home",
      "anchor_text": "Twitter"
    },
    {
      "url": "https://thehologram.io/",
      "anchor_text": "Web"
    },
    {
      "url": "https://medium.com/the-hologram",
      "anchor_text": "The Hologram"
    },
    {
      "url": "https://staratlas.com/",
      "anchor_text": "Star Atlas"
    }
  ],
  "open_questions": [
    "Which reported claims can be corroborated by primary or later sources?"
  ],
  "temporal_status": "HISTORICAL_SNAPSHOT",
  "current_validity": "REQUIRES_RECONCILIATION",
  "quality": {
    "extraction_confidence": "HIGH",
    "date_confidence": "HIGH",
    "author_confidence": "HIGH",
    "completeness": "COMPLETE",
    "manual_review_reasons": []
  },
  "retrieval": {
    "requested_url": "https://medium.com/the-hologram/former-star-atlas-cro-speak-on-departure-eb37dc95ff3",
    "final_url": "https://medium.com/the-hologram/former-star-atlas-cro-speak-on-departure-eb37dc95ff3",
    "http_status": 200,
    "content_type": "text/html; charset=utf-8",
    "response_size": 265504,
    "elapsed_ms": 686,
    "retrieval_mode": "LIVE",
    "archive_capture": null
  }
}
